{
    "Id": 432,
    "Title": "Art Society March Elections 2025",
    "Organisation": {
        "Id": 6131,
        "Name": "Art Society"
    },
    "Eligible": 174,
    "Voters": 15,
    "NonVoters": 159,
    "Votes": 56,
    "PostCount": 6,
    "CandidateCount": 7,
    "IndividualCandidateCount": 7,
    "DateGenerated": "2026-05-15T20:03:20.2824201+01:00",
    "Groups": [
        {
            "Name": "Age range",
            "Items": [
                {
                    "Name": "18 - 21",
                    "Voters": 12,
                    "NonVoters": 128,
                    "Eligible": 140,
                    "IsOtherItem": false,
                    "Turnout": 8.57142857142857,
                    "RelativeTurnout": 6.89655172413793
                },
                {
                    "Name": "22 - 25",
                    "Voters": 2,
                    "NonVoters": 24,
                    "Eligible": 26,
                    "IsOtherItem": false,
                    "Turnout": 7.69230769230769,
                    "RelativeTurnout": 1.14942528735632
                },
                {
                    "Name": "26 - 30",
                    "Voters": 1,
                    "NonVoters": 5,
                    "Eligible": 6,
                    "IsOtherItem": false,
                    "Turnout": 16.6666666666667,
                    "RelativeTurnout": 0.574712643678161
                },
                {
                    "Name": "Over 30",
                    "Voters": 0,
                    "NonVoters": 2,
                    "Eligible": 2,
                    "IsOtherItem": false,
                    "Turnout": 0.0,
                    "RelativeTurnout": 0.0
                }
            ]
        },
        {
            "Name": "Data source",
            "Items": [
                {
                    "Name": "FILE",
                    "Voters": 15,
                    "NonVoters": 159,
                    "Eligible": 174,
                    "IsOtherItem": false,
                    "Turnout": 8.62068965517241,
                    "RelativeTurnout": 8.62068965517241
                }
            ]
        },
        {
            "Name": "Fees status",
            "Items": [
                {
                    "Name": "All other values",
                    "Voters": 15,
                    "NonVoters": 159,
                    "Eligible": 174,
                    "IsOtherItem": true,
                    "Turnout": 8.62068965517241,
                    "RelativeTurnout": 8.62068965517241
                }
            ]
        },
        {
            "Name": "Mode of study",
            "Items": [
                {
                    "Name": "Full-time",
                    "Voters": 15,
                    "NonVoters": 155,
                    "Eligible": 170,
                    "IsOtherItem": false,
                    "Turnout": 8.82352941176471,
                    "RelativeTurnout": 8.62068965517241
                },
                {
                    "Name": "Part-time.",
                    "Voters": 0,
                    "NonVoters": 4,
                    "Eligible": 4,
                    "IsOtherItem": false,
                    "Turnout": 0.0,
                    "RelativeTurnout": 0.0
                },
                {
                    "Name": "Writing-up - previously full-time.",
                    "Voters": 0,
                    "NonVoters": 0,
                    "Eligible": 0,
                    "IsOtherItem": false,
                    "Turnout": 0.0,
                    "RelativeTurnout": 0.0
                }
            ]
        },
        {
            "Name": "Residency",
            "Items": [
                {
                    "Name": "Pritchatts Park Village",
                    "Voters": 0,
                    "NonVoters": 0,
                    "Eligible": 0,
                    "IsOtherItem": false,
                    "Turnout": 0.0,
                    "RelativeTurnout": 0.0
                },
                {
                    "Name": "Tennis Court",
                    "Voters": 0,
                    "NonVoters": 2,
                    "Eligible": 2,
                    "IsOtherItem": false,
                    "Turnout": 0.0,
                    "RelativeTurnout": 0.0
                }
            ]
        },
        {
            "Name": "Sex",
            "Items": [
                {
                    "Name": "F",
                    "Voters": 13,
                    "NonVoters": 141,
                    "Eligible": 154,
                    "IsOtherItem": false,
                    "Turnout": 8.44155844155844,
                    "RelativeTurnout": 7.47126436781609
                },
                {
                    "Name": "M",
                    "Voters": 2,
                    "NonVoters": 17,
                    "Eligible": 19,
                    "IsOtherItem": false,
                    "Turnout": 10.5263157894737,
                    "RelativeTurnout": 1.14942528735632
                },
                {
                    "Name": "N",
                    "Voters": 0,
                    "NonVoters": 1,
                    "Eligible": 1,
                    "IsOtherItem": false,
                    "Turnout": 0.0,
                    "RelativeTurnout": 0.0
                }
            ]
        },
        {
            "Name": "Student type",
            "Items": [
                {
                    "Name": "Postgraduate Research",
                    "Voters": 1,
                    "NonVoters": 6,
                    "Eligible": 7,
                    "IsOtherItem": false,
                    "Turnout": 14.2857142857143,
                    "RelativeTurnout": 0.574712643678161
                },
                {
                    "Name": "Postgraduate Taught",
                    "Voters": 0,
                    "NonVoters": 11,
                    "Eligible": 11,
                    "IsOtherItem": false,
                    "Turnout": 0.0,
                    "RelativeTurnout": 0.0
                },
                {
                    "Name": "Undergraduate",
                    "Voters": 14,
                    "NonVoters": 142,
                    "Eligible": 156,
                    "IsOtherItem": false,
                    "Turnout": 8.97435897435898,
                    "RelativeTurnout": 8.04597701149425
                }
            ]
        },
        {
            "Name": "Year of study",
            "Items": [
                {
                    "Name": "1st year",
                    "Voters": 7,
                    "NonVoters": 103,
                    "Eligible": 110,
                    "IsOtherItem": false,
                    "Turnout": 6.36363636363636,
                    "RelativeTurnout": 4.02298850574713
                },
                {
                    "Name": "2nd year",
                    "Voters": 5,
                    "NonVoters": 32,
                    "Eligible": 37,
                    "IsOtherItem": false,
                    "Turnout": 13.5135135135135,
                    "RelativeTurnout": 2.8735632183908
                },
                {
                    "Name": "3rd year",
                    "Voters": 2,
                    "NonVoters": 16,
                    "Eligible": 18,
                    "IsOtherItem": false,
                    "Turnout": 11.1111111111111,
                    "RelativeTurnout": 1.14942528735632
                },
                {
                    "Name": "4th year",
                    "Voters": 1,
                    "NonVoters": 6,
                    "Eligible": 7,
                    "IsOtherItem": false,
                    "Turnout": 14.2857142857143,
                    "RelativeTurnout": 0.574712643678161
                },
                {
                    "Name": "Foundation year",
                    "Voters": 0,
                    "NonVoters": 2,
                    "Eligible": 2,
                    "IsOtherItem": false,
                    "Turnout": 0.0,
                    "RelativeTurnout": 0.0
                }
            ]
        },
        {
            "Name": "Department",
            "Items": [
                {
                    "Name": "African Studies & Anthropology",
                    "Voters": 0,
                    "NonVoters": 2,
                    "Eligible": 2,
                    "IsOtherItem": false,
                    "Turnout": 0.0,
                    "RelativeTurnout": 0.0
                },
                {
                    "Name": "All other values",
                    "Voters": 0,
                    "NonVoters": 2,
                    "Eligible": 2,
                    "IsOtherItem": true,
                    "Turnout": 0.0,
                    "RelativeTurnout": 0.0
                },
                {
                    "Name": "Art Hist, Cur and Vis Studies",
                    "Voters": 2,
                    "NonVoters": 10,
                    "Eligible": 12,
                    "IsOtherItem": false,
                    "Turnout": 16.6666666666667,
                    "RelativeTurnout": 1.14942528735632
                },
                {
                    "Name": "Biomedical Sciences",
                    "Voters": 0,
                    "NonVoters": 2,
                    "Eligible": 2,
                    "IsOtherItem": false,
                    "Turnout": 0.0,
                    "RelativeTurnout": 0.0
                },
                {
                    "Name": "Birmingham International Acad",
                    "Voters": 0,
                    "NonVoters": 2,
                    "Eligible": 2,
                    "IsOtherItem": false,
                    "Turnout": 0.0,
                    "RelativeTurnout": 0.0
                },
                {
                    "Name": "Birmingham Medical School",
                    "Voters": 2,
                    "NonVoters": 1,
                    "Eligible": 3,
                    "IsOtherItem": false,
                    "Turnout": 66.6666666666666,
                    "RelativeTurnout": 1.14942528735632
                },
                {
                    "Name": "Chemical Engineering",
                    "Voters": 0,
                    "NonVoters": 2,
                    "Eligible": 2,
                    "IsOtherItem": false,
                    "Turnout": 0.0,
                    "RelativeTurnout": 0.0
                },
                {
                    "Name": "Chemistry",
                    "Voters": 1,
                    "NonVoters": 4,
                    "Eligible": 5,
                    "IsOtherItem": false,
                    "Turnout": 20.0,
                    "RelativeTurnout": 0.574712643678161
                },
                {
                    "Name": "Civil Engineering",
                    "Voters": 0,
                    "NonVoters": 3,
                    "Eligible": 3,
                    "IsOtherItem": false,
                    "Turnout": 0.0,
                    "RelativeTurnout": 0.0
                },
                {
                    "Name": "Classics, AH and Archaeology",
                    "Voters": 0,
                    "NonVoters": 5,
                    "Eligible": 5,
                    "IsOtherItem": false,
                    "Turnout": 0.0,
                    "RelativeTurnout": 0.0
                },
                {
                    "Name": "Computer Science",
                    "Voters": 0,
                    "NonVoters": 1,
                    "Eligible": 1,
                    "IsOtherItem": false,
                    "Turnout": 0.0,
                    "RelativeTurnout": 0.0
                },
                {
                    "Name": "Dentistry",
                    "Voters": 0,
                    "NonVoters": 1,
                    "Eligible": 1,
                    "IsOtherItem": false,
                    "Turnout": 0.0,
                    "RelativeTurnout": 0.0
                },
                {
                    "Name": "Earth and Environ Sciences",
                    "Voters": 1,
                    "NonVoters": 7,
                    "Eligible": 8,
                    "IsOtherItem": false,
                    "Turnout": 12.5,
                    "RelativeTurnout": 0.574712643678161
                },
                {
                    "Name": "Economics",
                    "Voters": 0,
                    "NonVoters": 3,
                    "Eligible": 3,
                    "IsOtherItem": false,
                    "Turnout": 0.0,
                    "RelativeTurnout": 0.0
                },
                {
                    "Name": "Education & Social Justice",
                    "Voters": 0,
                    "NonVoters": 1,
                    "Eligible": 1,
                    "IsOtherItem": false,
                    "Turnout": 0.0,
                    "RelativeTurnout": 0.0
                },
                {
                    "Name": "Elec, Elec & Sys Engineering",
                    "Voters": 0,
                    "NonVoters": 2,
                    "Eligible": 2,
                    "IsOtherItem": false,
                    "Turnout": 0.0,
                    "RelativeTurnout": 0.0
                },
                {
                    "Name": "English Literature",
                    "Voters": 1,
                    "NonVoters": 11,
                    "Eligible": 12,
                    "IsOtherItem": false,
                    "Turnout": 8.33333333333333,
                    "RelativeTurnout": 0.574712643678161
                },
                {
                    "Name": "Film and Creative Writing",
                    "Voters": 0,
                    "NonVoters": 6,
                    "Eligible": 6,
                    "IsOtherItem": false,
                    "Turnout": 0.0,
                    "RelativeTurnout": 0.0
                },
                {
                    "Name": "Geography",
                    "Voters": 0,
                    "NonVoters": 5,
                    "Eligible": 5,
                    "IsOtherItem": false,
                    "Turnout": 0.0,
                    "RelativeTurnout": 0.0
                },
                {
                    "Name": "History",
                    "Voters": 1,
                    "NonVoters": 1,
                    "Eligible": 2,
                    "IsOtherItem": false,
                    "Turnout": 50.0,
                    "RelativeTurnout": 0.574712643678161
                },
                {
                    "Name": "Inst of Cancer / Genomic Sci",
                    "Voters": 0,
                    "NonVoters": 1,
                    "Eligible": 1,
                    "IsOtherItem": false,
                    "Turnout": 0.0,
                    "RelativeTurnout": 0.0
                },
                {
                    "Name": "Inst of Inflammation / Ageing",
                    "Voters": 0,
                    "NonVoters": 1,
                    "Eligible": 1,
                    "IsOtherItem": false,
                    "Turnout": 0.0,
                    "RelativeTurnout": 0.0
                },
                {
                    "Name": "International Development",
                    "Voters": 0,
                    "NonVoters": 1,
                    "Eligible": 1,
                    "IsOtherItem": false,
                    "Turnout": 0.0,
                    "RelativeTurnout": 0.0
                },
                {
                    "Name": "Law",
                    "Voters": 1,
                    "NonVoters": 6,
                    "Eligible": 7,
                    "IsOtherItem": false,
                    "Turnout": 14.2857142857143,
                    "RelativeTurnout": 0.574712643678161
                },
                {
                    "Name": "Management",
                    "Voters": 0,
                    "NonVoters": 3,
                    "Eligible": 3,
                    "IsOtherItem": false,
                    "Turnout": 0.0,
                    "RelativeTurnout": 0.0
                },
                {
                    "Name": "Marketing",
                    "Voters": 0,
                    "NonVoters": 2,
                    "Eligible": 2,
                    "IsOtherItem": false,
                    "Turnout": 0.0,
                    "RelativeTurnout": 0.0
                },
                {
                    "Name": "Mathematics",
                    "Voters": 1,
                    "NonVoters": 3,
                    "Eligible": 4,
                    "IsOtherItem": false,
                    "Turnout": 25.0,
                    "RelativeTurnout": 0.574712643678161
                },
                {
                    "Name": "Mechanical Engineering",
                    "Voters": 0,
                    "NonVoters": 3,
                    "Eligible": 3,
                    "IsOtherItem": false,
                    "Turnout": 0.0,
                    "RelativeTurnout": 0.0
                },
                {
                    "Name": "Metallurgy & Materials",
                    "Voters": 0,
                    "NonVoters": 3,
                    "Eligible": 3,
                    "IsOtherItem": false,
                    "Turnout": 0.0,
                    "RelativeTurnout": 0.0
                },
                {
                    "Name": "Modern Languages",
                    "Voters": 1,
                    "NonVoters": 3,
                    "Eligible": 4,
                    "IsOtherItem": false,
                    "Turnout": 25.0,
                    "RelativeTurnout": 0.574712643678161
                },
                {
                    "Name": "Music",
                    "Voters": 0,
                    "NonVoters": 2,
                    "Eligible": 2,
                    "IsOtherItem": false,
                    "Turnout": 0.0,
                    "RelativeTurnout": 0.0
                },
                {
                    "Name": "Nursing and Midwifery",
                    "Voters": 0,
                    "NonVoters": 1,
                    "Eligible": 1,
                    "IsOtherItem": false,
                    "Turnout": 0.0,
                    "RelativeTurnout": 0.0
                },
                {
                    "Name": "Pharmacy",
                    "Voters": 0,
                    "NonVoters": 1,
                    "Eligible": 1,
                    "IsOtherItem": false,
                    "Turnout": 0.0,
                    "RelativeTurnout": 0.0
                },
                {
                    "Name": "Phil, Theol & Religion",
                    "Voters": 0,
                    "NonVoters": 5,
                    "Eligible": 5,
                    "IsOtherItem": false,
                    "Turnout": 0.0,
                    "RelativeTurnout": 0.0
                },
                {
                    "Name": "Philosophy",
                    "Voters": 1,
                    "NonVoters": 2,
                    "Eligible": 3,
                    "IsOtherItem": false,
                    "Turnout": 33.3333333333333,
                    "RelativeTurnout": 0.574712643678161
                },
                {
                    "Name": "Physics & Astronomy",
                    "Voters": 2,
                    "NonVoters": 5,
                    "Eligible": 7,
                    "IsOtherItem": false,
                    "Turnout": 28.5714285714286,
                    "RelativeTurnout": 1.14942528735632
                },
                {
                    "Name": "Physiotherapy",
                    "Voters": 0,
                    "NonVoters": 1,
                    "Eligible": 1,
                    "IsOtherItem": false,
                    "Turnout": 0.0,
                    "RelativeTurnout": 0.0
                },
                {
                    "Name": "Political Sci & Intern'tl Stud",
                    "Voters": 0,
                    "NonVoters": 9,
                    "Eligible": 9,
                    "IsOtherItem": false,
                    "Turnout": 0.0,
                    "RelativeTurnout": 0.0
                },
                {
                    "Name": "School of Biosciences",
                    "Voters": 0,
                    "NonVoters": 8,
                    "Eligible": 8,
                    "IsOtherItem": false,
                    "Turnout": 0.0,
                    "RelativeTurnout": 0.0
                },
                {
                    "Name": "School of Psychology",
                    "Voters": 1,
                    "NonVoters": 18,
                    "Eligible": 19,
                    "IsOtherItem": false,
                    "Turnout": 5.26315789473684,
                    "RelativeTurnout": 0.574712643678161
                },
                {
                    "Name": "Soc Policy, Sociology & Crimin",
                    "Voters": 0,
                    "NonVoters": 8,
                    "Eligible": 8,
                    "IsOtherItem": false,
                    "Turnout": 0.0,
                    "RelativeTurnout": 0.0
                },
                {
                    "Name": "Teacher Education",
                    "Voters": 0,
                    "NonVoters": 1,
                    "Eligible": 1,
                    "IsOtherItem": false,
                    "Turnout": 0.0,
                    "RelativeTurnout": 0.0
                },
                {
                    "Name": "Theology and Religion",
                    "Voters": 0,
                    "NonVoters": 1,
                    "Eligible": 1,
                    "IsOtherItem": false,
                    "Turnout": 0.0,
                    "RelativeTurnout": 0.0
                }
            ]
        },
        {
            "Name": "College",
            "Items": [
                {
                    "Name": "All other values",
                    "Voters": 0,
                    "NonVoters": 2,
                    "Eligible": 2,
                    "IsOtherItem": true,
                    "Turnout": 0.0,
                    "RelativeTurnout": 0.0
                },
                {
                    "Name": "College of Arts and Law",
                    "Voters": 7,
                    "NonVoters": 56,
                    "Eligible": 63,
                    "IsOtherItem": false,
                    "Turnout": 11.1111111111111,
                    "RelativeTurnout": 4.02298850574713
                },
                {
                    "Name": "College of Engineering and Physical Sciences",
                    "Voters": 4,
                    "NonVoters": 26,
                    "Eligible": 30,
                    "IsOtherItem": false,
                    "Turnout": 13.3333333333333,
                    "RelativeTurnout": 2.29885057471264
                },
                {
                    "Name": "College of Life and Environmental Sciences",
                    "Voters": 2,
                    "NonVoters": 39,
                    "Eligible": 41,
                    "IsOtherItem": false,
                    "Turnout": 4.8780487804878,
                    "RelativeTurnout": 1.14942528735632
                },
                {
                    "Name": "College of Medicine and Health",
                    "Voters": 2,
                    "NonVoters": 8,
                    "Eligible": 10,
                    "IsOtherItem": false,
                    "Turnout": 20.0,
                    "RelativeTurnout": 1.14942528735632
                },
                {
                    "Name": "College of Social Sciences",
                    "Voters": 0,
                    "NonVoters": 28,
                    "Eligible": 28,
                    "IsOtherItem": false,
                    "Turnout": 0.0,
                    "RelativeTurnout": 0.0
                }
            ]
        },
        {
            "Name": "Course Code",
            "Items": [
                {
                    "Name": "All other values",
                    "Voters": 15,
                    "NonVoters": 159,
                    "Eligible": 174,
                    "IsOtherItem": true,
                    "Turnout": 8.62068965517241,
                    "RelativeTurnout": 8.62068965517241
                }
            ]
        }
    ],
    "Turnout": 8.62068965517241
}