{
    "Id": 537,
    "Title": "Planning Society May Elections 2025",
    "Organisation": {
        "Id": 11898,
        "Name": "Planning"
    },
    "Eligible": 38,
    "Voters": 1,
    "NonVoters": 37,
    "Votes": 1,
    "PostCount": 1,
    "CandidateCount": 1,
    "IndividualCandidateCount": 1,
    "DateGenerated": "2026-05-15T20:03:46.6726272+01:00",
    "Groups": [
        {
            "Name": "Age range",
            "Items": [
                {
                    "Name": "18 - 21",
                    "Voters": 1,
                    "NonVoters": 25,
                    "Eligible": 26,
                    "IsOtherItem": false,
                    "Turnout": 3.84615384615385,
                    "RelativeTurnout": 2.63157894736842
                },
                {
                    "Name": "22 - 25",
                    "Voters": 0,
                    "NonVoters": 10,
                    "Eligible": 10,
                    "IsOtherItem": false,
                    "Turnout": 0.0,
                    "RelativeTurnout": 0.0
                },
                {
                    "Name": "Over 30",
                    "Voters": 0,
                    "NonVoters": 2,
                    "Eligible": 2,
                    "IsOtherItem": false,
                    "Turnout": 0.0,
                    "RelativeTurnout": 0.0
                }
            ]
        },
        {
            "Name": "Data source",
            "Items": [
                {
                    "Name": "FILE",
                    "Voters": 1,
                    "NonVoters": 37,
                    "Eligible": 38,
                    "IsOtherItem": false,
                    "Turnout": 2.63157894736842,
                    "RelativeTurnout": 2.63157894736842
                }
            ]
        },
        {
            "Name": "Fees status",
            "Items": [
                {
                    "Name": "All other values",
                    "Voters": 1,
                    "NonVoters": 37,
                    "Eligible": 38,
                    "IsOtherItem": true,
                    "Turnout": 2.63157894736842,
                    "RelativeTurnout": 2.63157894736842
                }
            ]
        },
        {
            "Name": "Mode of study",
            "Items": [
                {
                    "Name": "Full-time",
                    "Voters": 1,
                    "NonVoters": 36,
                    "Eligible": 37,
                    "IsOtherItem": false,
                    "Turnout": 2.7027027027027,
                    "RelativeTurnout": 2.63157894736842
                },
                {
                    "Name": "Part-time.",
                    "Voters": 0,
                    "NonVoters": 1,
                    "Eligible": 1,
                    "IsOtherItem": false,
                    "Turnout": 0.0,
                    "RelativeTurnout": 0.0
                },
                {
                    "Name": "Writing-up - previously full-time.",
                    "Voters": 0,
                    "NonVoters": 0,
                    "Eligible": 0,
                    "IsOtherItem": false,
                    "Turnout": 0.0,
                    "RelativeTurnout": 0.0
                }
            ]
        },
        {
            "Name": "Residency",
            "Items": [
                {
                    "Name": "Host - The Metalworks",
                    "Voters": 0,
                    "NonVoters": 1,
                    "Eligible": 1,
                    "IsOtherItem": false,
                    "Turnout": 0.0,
                    "RelativeTurnout": 0.0
                },
                {
                    "Name": "Pritchatts Park Village",
                    "Voters": 0,
                    "NonVoters": 0,
                    "Eligible": 0,
                    "IsOtherItem": false,
                    "Turnout": 0.0,
                    "RelativeTurnout": 0.0
                }
            ]
        },
        {
            "Name": "Sex",
            "Items": [
                {
                    "Name": "F",
                    "Voters": 1,
                    "NonVoters": 19,
                    "Eligible": 20,
                    "IsOtherItem": false,
                    "Turnout": 5.0,
                    "RelativeTurnout": 2.63157894736842
                },
                {
                    "Name": "M",
                    "Voters": 0,
                    "NonVoters": 17,
                    "Eligible": 17,
                    "IsOtherItem": false,
                    "Turnout": 0.0,
                    "RelativeTurnout": 0.0
                },
                {
                    "Name": "N",
                    "Voters": 0,
                    "NonVoters": 1,
                    "Eligible": 1,
                    "IsOtherItem": false,
                    "Turnout": 0.0,
                    "RelativeTurnout": 0.0
                }
            ]
        },
        {
            "Name": "Student type",
            "Items": [
                {
                    "Name": "Postgraduate Taught",
                    "Voters": 0,
                    "NonVoters": 9,
                    "Eligible": 9,
                    "IsOtherItem": false,
                    "Turnout": 0.0,
                    "RelativeTurnout": 0.0
                },
                {
                    "Name": "Undergraduate",
                    "Voters": 1,
                    "NonVoters": 28,
                    "Eligible": 29,
                    "IsOtherItem": false,
                    "Turnout": 3.44827586206896,
                    "RelativeTurnout": 2.63157894736842
                }
            ]
        },
        {
            "Name": "Year of study",
            "Items": [
                {
                    "Name": "1st year",
                    "Voters": 0,
                    "NonVoters": 16,
                    "Eligible": 16,
                    "IsOtherItem": false,
                    "Turnout": 0.0,
                    "RelativeTurnout": 0.0
                },
                {
                    "Name": "2nd year",
                    "Voters": 1,
                    "NonVoters": 12,
                    "Eligible": 13,
                    "IsOtherItem": false,
                    "Turnout": 7.69230769230769,
                    "RelativeTurnout": 2.63157894736842
                },
                {
                    "Name": "3rd year",
                    "Voters": 0,
                    "NonVoters": 8,
                    "Eligible": 8,
                    "IsOtherItem": false,
                    "Turnout": 0.0,
                    "RelativeTurnout": 0.0
                },
                {
                    "Name": "4th year",
                    "Voters": 0,
                    "NonVoters": 1,
                    "Eligible": 1,
                    "IsOtherItem": false,
                    "Turnout": 0.0,
                    "RelativeTurnout": 0.0
                }
            ]
        },
        {
            "Name": "Department",
            "Items": [
                {
                    "Name": "Geography",
                    "Voters": 1,
                    "NonVoters": 37,
                    "Eligible": 38,
                    "IsOtherItem": false,
                    "Turnout": 2.63157894736842,
                    "RelativeTurnout": 2.63157894736842
                }
            ]
        },
        {
            "Name": "College",
            "Items": [
                {
                    "Name": "College of Life and Environmental Sciences",
                    "Voters": 1,
                    "NonVoters": 37,
                    "Eligible": 38,
                    "IsOtherItem": false,
                    "Turnout": 2.63157894736842,
                    "RelativeTurnout": 2.63157894736842
                }
            ]
        },
        {
            "Name": "Course Code",
            "Items": [
                {
                    "Name": "All other values",
                    "Voters": 1,
                    "NonVoters": 37,
                    "Eligible": 38,
                    "IsOtherItem": true,
                    "Turnout": 2.63157894736842,
                    "RelativeTurnout": 2.63157894736842
                }
            ]
        }
    ],
    "Turnout": 2.63157894736842
}