{
    "Id": 543,
    "Title": "Indonesian May Election 2025",
    "Organisation": {
        "Id": 6795,
        "Name": "Indonesian"
    },
    "Eligible": 45,
    "Voters": 0,
    "NonVoters": 45,
    "Votes": 0,
    "PostCount": 3,
    "CandidateCount": 0,
    "IndividualCandidateCount": 0,
    "DateGenerated": "2026-05-15T20:03:48.1676392+01:00",
    "Groups": [
        {
            "Name": "Age range",
            "Items": [
                {
                    "Name": "18 - 21",
                    "Voters": 0,
                    "NonVoters": 25,
                    "Eligible": 25,
                    "IsOtherItem": false,
                    "Turnout": 0.0,
                    "RelativeTurnout": 0.0
                },
                {
                    "Name": "22 - 25",
                    "Voters": 0,
                    "NonVoters": 8,
                    "Eligible": 8,
                    "IsOtherItem": false,
                    "Turnout": 0.0,
                    "RelativeTurnout": 0.0
                },
                {
                    "Name": "26 - 30",
                    "Voters": 0,
                    "NonVoters": 10,
                    "Eligible": 10,
                    "IsOtherItem": false,
                    "Turnout": 0.0,
                    "RelativeTurnout": 0.0
                },
                {
                    "Name": "Over 30",
                    "Voters": 0,
                    "NonVoters": 2,
                    "Eligible": 2,
                    "IsOtherItem": false,
                    "Turnout": 0.0,
                    "RelativeTurnout": 0.0
                }
            ]
        },
        {
            "Name": "Data source",
            "Items": [
                {
                    "Name": "FILE",
                    "Voters": 0,
                    "NonVoters": 45,
                    "Eligible": 45,
                    "IsOtherItem": false,
                    "Turnout": 0.0,
                    "RelativeTurnout": 0.0
                }
            ]
        },
        {
            "Name": "Fees status",
            "Items": [
                {
                    "Name": "All other values",
                    "Voters": 0,
                    "NonVoters": 45,
                    "Eligible": 45,
                    "IsOtherItem": true,
                    "Turnout": 0.0,
                    "RelativeTurnout": 0.0
                }
            ]
        },
        {
            "Name": "Mode of study",
            "Items": [
                {
                    "Name": "Full-time",
                    "Voters": 0,
                    "NonVoters": 45,
                    "Eligible": 45,
                    "IsOtherItem": false,
                    "Turnout": 0.0,
                    "RelativeTurnout": 0.0
                },
                {
                    "Name": "Writing-up - previously full-time.",
                    "Voters": 0,
                    "NonVoters": 0,
                    "Eligible": 0,
                    "IsOtherItem": false,
                    "Turnout": 0.0,
                    "RelativeTurnout": 0.0
                }
            ]
        },
        {
            "Name": "Residency",
            "Items": [
                {
                    "Name": "Pritchatts Park Village",
                    "Voters": 0,
                    "NonVoters": 0,
                    "Eligible": 0,
                    "IsOtherItem": false,
                    "Turnout": 0.0,
                    "RelativeTurnout": 0.0
                }
            ]
        },
        {
            "Name": "Sex",
            "Items": [
                {
                    "Name": "F",
                    "Voters": 0,
                    "NonVoters": 21,
                    "Eligible": 21,
                    "IsOtherItem": false,
                    "Turnout": 0.0,
                    "RelativeTurnout": 0.0
                },
                {
                    "Name": "M",
                    "Voters": 0,
                    "NonVoters": 24,
                    "Eligible": 24,
                    "IsOtherItem": false,
                    "Turnout": 0.0,
                    "RelativeTurnout": 0.0
                }
            ]
        },
        {
            "Name": "Student type",
            "Items": [
                {
                    "Name": "Postgraduate Research",
                    "Voters": 0,
                    "NonVoters": 3,
                    "Eligible": 3,
                    "IsOtherItem": false,
                    "Turnout": 0.0,
                    "RelativeTurnout": 0.0
                },
                {
                    "Name": "Postgraduate Taught",
                    "Voters": 0,
                    "NonVoters": 13,
                    "Eligible": 13,
                    "IsOtherItem": false,
                    "Turnout": 0.0,
                    "RelativeTurnout": 0.0
                },
                {
                    "Name": "Undergraduate",
                    "Voters": 0,
                    "NonVoters": 29,
                    "Eligible": 29,
                    "IsOtherItem": false,
                    "Turnout": 0.0,
                    "RelativeTurnout": 0.0
                }
            ]
        },
        {
            "Name": "Year of study",
            "Items": [
                {
                    "Name": "1st year",
                    "Voters": 0,
                    "NonVoters": 20,
                    "Eligible": 20,
                    "IsOtherItem": false,
                    "Turnout": 0.0,
                    "RelativeTurnout": 0.0
                },
                {
                    "Name": "2nd year",
                    "Voters": 0,
                    "NonVoters": 12,
                    "Eligible": 12,
                    "IsOtherItem": false,
                    "Turnout": 0.0,
                    "RelativeTurnout": 0.0
                },
                {
                    "Name": "3rd year",
                    "Voters": 0,
                    "NonVoters": 10,
                    "Eligible": 10,
                    "IsOtherItem": false,
                    "Turnout": 0.0,
                    "RelativeTurnout": 0.0
                },
                {
                    "Name": "4th year",
                    "Voters": 0,
                    "NonVoters": 2,
                    "Eligible": 2,
                    "IsOtherItem": false,
                    "Turnout": 0.0,
                    "RelativeTurnout": 0.0
                },
                {
                    "Name": "Foundation year",
                    "Voters": 0,
                    "NonVoters": 1,
                    "Eligible": 1,
                    "IsOtherItem": false,
                    "Turnout": 0.0,
                    "RelativeTurnout": 0.0
                }
            ]
        },
        {
            "Name": "Department",
            "Items": [
                {
                    "Name": "Accounting",
                    "Voters": 0,
                    "NonVoters": 2,
                    "Eligible": 2,
                    "IsOtherItem": false,
                    "Turnout": 0.0,
                    "RelativeTurnout": 0.0
                },
                {
                    "Name": "All other values",
                    "Voters": 0,
                    "NonVoters": 1,
                    "Eligible": 1,
                    "IsOtherItem": true,
                    "Turnout": 0.0,
                    "RelativeTurnout": 0.0
                },
                {
                    "Name": "Birmingham International Acad",
                    "Voters": 0,
                    "NonVoters": 1,
                    "Eligible": 1,
                    "IsOtherItem": false,
                    "Turnout": 0.0,
                    "RelativeTurnout": 0.0
                },
                {
                    "Name": "Birmingham Medical School",
                    "Voters": 0,
                    "NonVoters": 1,
                    "Eligible": 1,
                    "IsOtherItem": false,
                    "Turnout": 0.0,
                    "RelativeTurnout": 0.0
                },
                {
                    "Name": "Chemical Engineering",
                    "Voters": 0,
                    "NonVoters": 4,
                    "Eligible": 4,
                    "IsOtherItem": false,
                    "Turnout": 0.0,
                    "RelativeTurnout": 0.0
                },
                {
                    "Name": "Chemistry",
                    "Voters": 0,
                    "NonVoters": 1,
                    "Eligible": 1,
                    "IsOtherItem": false,
                    "Turnout": 0.0,
                    "RelativeTurnout": 0.0
                },
                {
                    "Name": "Civil Engineering",
                    "Voters": 0,
                    "NonVoters": 1,
                    "Eligible": 1,
                    "IsOtherItem": false,
                    "Turnout": 0.0,
                    "RelativeTurnout": 0.0
                },
                {
                    "Name": "Computer Science",
                    "Voters": 0,
                    "NonVoters": 9,
                    "Eligible": 9,
                    "IsOtherItem": false,
                    "Turnout": 0.0,
                    "RelativeTurnout": 0.0
                },
                {
                    "Name": "Earth and Environ Sciences",
                    "Voters": 0,
                    "NonVoters": 1,
                    "Eligible": 1,
                    "IsOtherItem": false,
                    "Turnout": 0.0,
                    "RelativeTurnout": 0.0
                },
                {
                    "Name": "Education & Social Justice",
                    "Voters": 0,
                    "NonVoters": 1,
                    "Eligible": 1,
                    "IsOtherItem": false,
                    "Turnout": 0.0,
                    "RelativeTurnout": 0.0
                },
                {
                    "Name": "Elec, Elec & Sys Engineering",
                    "Voters": 0,
                    "NonVoters": 2,
                    "Eligible": 2,
                    "IsOtherItem": false,
                    "Turnout": 0.0,
                    "RelativeTurnout": 0.0
                },
                {
                    "Name": "Film and Creative Writing",
                    "Voters": 0,
                    "NonVoters": 1,
                    "Eligible": 1,
                    "IsOtherItem": false,
                    "Turnout": 0.0,
                    "RelativeTurnout": 0.0
                },
                {
                    "Name": "Inst of Cancer / Genomic Sci",
                    "Voters": 0,
                    "NonVoters": 1,
                    "Eligible": 1,
                    "IsOtherItem": false,
                    "Turnout": 0.0,
                    "RelativeTurnout": 0.0
                },
                {
                    "Name": "Law",
                    "Voters": 0,
                    "NonVoters": 3,
                    "Eligible": 3,
                    "IsOtherItem": false,
                    "Turnout": 0.0,
                    "RelativeTurnout": 0.0
                },
                {
                    "Name": "Management",
                    "Voters": 0,
                    "NonVoters": 10,
                    "Eligible": 10,
                    "IsOtherItem": false,
                    "Turnout": 0.0,
                    "RelativeTurnout": 0.0
                },
                {
                    "Name": "Marketing",
                    "Voters": 0,
                    "NonVoters": 1,
                    "Eligible": 1,
                    "IsOtherItem": false,
                    "Turnout": 0.0,
                    "RelativeTurnout": 0.0
                },
                {
                    "Name": "Mathematics",
                    "Voters": 0,
                    "NonVoters": 2,
                    "Eligible": 2,
                    "IsOtherItem": false,
                    "Turnout": 0.0,
                    "RelativeTurnout": 0.0
                },
                {
                    "Name": "Political Sci & Intern'tl Stud",
                    "Voters": 0,
                    "NonVoters": 1,
                    "Eligible": 1,
                    "IsOtherItem": false,
                    "Turnout": 0.0,
                    "RelativeTurnout": 0.0
                },
                {
                    "Name": "School of Biosciences",
                    "Voters": 0,
                    "NonVoters": 1,
                    "Eligible": 1,
                    "IsOtherItem": false,
                    "Turnout": 0.0,
                    "RelativeTurnout": 0.0
                },
                {
                    "Name": "Theology and Religion",
                    "Voters": 0,
                    "NonVoters": 1,
                    "Eligible": 1,
                    "IsOtherItem": false,
                    "Turnout": 0.0,
                    "RelativeTurnout": 0.0
                }
            ]
        },
        {
            "Name": "College",
            "Items": [
                {
                    "Name": "All other values",
                    "Voters": 0,
                    "NonVoters": 1,
                    "Eligible": 1,
                    "IsOtherItem": true,
                    "Turnout": 0.0,
                    "RelativeTurnout": 0.0
                },
                {
                    "Name": "College of Arts and Law",
                    "Voters": 0,
                    "NonVoters": 6,
                    "Eligible": 6,
                    "IsOtherItem": false,
                    "Turnout": 0.0,
                    "RelativeTurnout": 0.0
                },
                {
                    "Name": "College of Engineering and Physical Sciences",
                    "Voters": 0,
                    "NonVoters": 19,
                    "Eligible": 19,
                    "IsOtherItem": false,
                    "Turnout": 0.0,
                    "RelativeTurnout": 0.0
                },
                {
                    "Name": "College of Life and Environmental Sciences",
                    "Voters": 0,
                    "NonVoters": 2,
                    "Eligible": 2,
                    "IsOtherItem": false,
                    "Turnout": 0.0,
                    "RelativeTurnout": 0.0
                },
                {
                    "Name": "College of Medicine and Health",
                    "Voters": 0,
                    "NonVoters": 2,
                    "Eligible": 2,
                    "IsOtherItem": false,
                    "Turnout": 0.0,
                    "RelativeTurnout": 0.0
                },
                {
                    "Name": "College of Social Sciences",
                    "Voters": 0,
                    "NonVoters": 15,
                    "Eligible": 15,
                    "IsOtherItem": false,
                    "Turnout": 0.0,
                    "RelativeTurnout": 0.0
                }
            ]
        },
        {
            "Name": "Course Code",
            "Items": [
                {
                    "Name": "All other values",
                    "Voters": 0,
                    "NonVoters": 45,
                    "Eligible": 45,
                    "IsOtherItem": true,
                    "Turnout": 0.0,
                    "RelativeTurnout": 0.0
                }
            ]
        }
    ],
    "Turnout": 0.0
}